KennyPavan/KennyPavan.py
KennyPavan/__init__.py
KennyPavan-1.0.0.dist-info/METADATA
KennyPavan-1.0.0.dist-info/WHEEL
KennyPavan-1.0.0.dist-info/top_level.txt
KennyPavan-1.0.0.dist-info/RECORD
