Metadata-Version: 2.1
Name: KennyPavan
Version: 1.0.0
Summary: Kenny Pavan: About, projects, and resume as a PyPi package.
Home-page: https://github.com/kennypavan/kennypavan
Author: Kenny Pavan
Author-email: pavan@protonmail.com
Classifier: Programming Language :: Python :: 3
Classifier: License :: OSI Approved :: MIT License
Classifier: Operating System :: OS Independent
Requires-Python: >=3.7
